README.rst
setup.py
feing_core.egg-info/PKG-INFO
feing_core.egg-info/SOURCES.txt
feing_core.egg-info/dependency_links.txt
feing_core.egg-info/not-zip-safe
feing_core.egg-info/requires.txt
feing_core.egg-info/top_level.txt
libs/__init__.py
libs/files.py
libs/json.py
libs/proxies.py
libs/sort.py
wrappers/__init__.py
wrappers/downloader.py
wrappers/request.py
wrappers/saver.py
wrappers/url_manager.py